LICENSE
pyproject.toml
imagenius/__init__.py
imagenius/cli.py
imagenius/models/__init__.py
imagenius/models/resnet.py
imagenius/www/index.html
imagenius/www/assets/css/materialize.css
imagenius/www/assets/css/materialize.min.css
imagenius/www/assets/css/style.css
imagenius/www/assets/js/app.js
imagenius/www/assets/js/materialize.js
imagenius/www/assets/js/materialize.min.js
imagenius-0.0.2.dist-info/METADATA
imagenius-0.0.2.dist-info/WHEEL
imagenius-0.0.2.dist-info/entry_points.txt
imagenius-0.0.2.dist-info/licenses/LICENSE
imagenius-0.0.2.dist-info/RECORD
