Metadata-Version: 2.1
Name: imagenius
Version: 0.0.2
Summary: Automatically tag images based on their content.
License-Expression: MIT
License-File: LICENSE
Requires-Python: >=3.9
Requires-Dist: black
Requires-Dist: flask
Requires-Dist: flask-cors
Requires-Dist: pillow
Requires-Dist: requests
Requires-Dist: torch
Requires-Dist: transformers
